scaler_pics/__init__.py
scaler_pics/scaler.py
scaler_pics-1.0.2.dist-info/LICENSE
scaler_pics-1.0.2.dist-info/METADATA
scaler_pics-1.0.2.dist-info/WHEEL
scaler_pics-1.0.2.dist-info/top_level.txt
scaler_pics-1.0.2.dist-info/RECORD
