Metadata-Version: 2.1
Name: scaler-pics
Version: 1.0.2
Summary: A Python library for image scaling, conversion and document thumbnail generation.
Home-page: https://github.com/scaler-pics/scaler.pics-py
Author: Matej Ukmar
Author-email: matejukmar@gmail.com
Classifier: Programming Language :: Python :: 3
Classifier: License :: OSI Approved :: MIT License
Classifier: Operating System :: OS Independent
Requires-Python: >=3.6
License-File: LICENSE
Requires-Dist: requests
Requires-Dist: aiohttp
Requires-Dist: PyJWT
